test_with_obsidian_graph_1/__init__.py
test_with_obsidian_graph_1/core.py
test_with_obsidian_graph_1-0.1.1.dist-info/METADATA
test_with_obsidian_graph_1-0.1.1.dist-info/WHEEL
test_with_obsidian_graph_1-0.1.1.dist-info/top_level.txt
test_with_obsidian_graph_1-0.1.1.dist-info/RECORD
